atash/__init__.py
atash/atash.py
atash-0.1.8.dist-info/METADATA
atash-0.1.8.dist-info/WHEEL
atash-0.1.8.dist-info/top_level.txt
atash-0.1.8.dist-info/RECORD
